MANIFEST.in
README.md
broadcast
setup.py
broadcaster/__init__.py
broadcaster/engine.py
broadcaster/plugin.py
broadcaster/terminal_ui.py
broadcaster/ui.py
broadcaster/plugins/__init__.py
broadcaster/plugins/mail.py
broadcaster/plugins/twitter.py
python_broadcaster.egg-info/PKG-INFO
python_broadcaster.egg-info/SOURCES.txt
python_broadcaster.egg-info/dependency_links.txt
python_broadcaster.egg-info/requires.txt
python_broadcaster.egg-info/top_level.txt