Metadata-Version: 1.0
Name: python-broadcaster
Version: 1.0.1
Summary: Broadcaster helps to post messages to different networking entities
Home-page: https://github.com/niyaspavil/Broadcaster
Author: Gorbin, Niyas, Vinayak
Author-email: broadcaster.thelycaeum@gmail.com
License: UNKNOWN
Platform: UNKNOWN
